active_911/__init__.py
active_911/client.py
active911_python-0.0.5.dist-info/LICENSE
active911_python-0.0.5.dist-info/METADATA
active911_python-0.0.5.dist-info/WHEEL
active911_python-0.0.5.dist-info/top_level.txt
active911_python-0.0.5.dist-info/RECORD
