Metadata-Version: 2.1
Name: active911-python
Version: 0.0.5
Summary: Python bindings for active911 API
Home-page: https://github.com/dc105297/active911_python
Author: David Chason
Author-email: davidchason@gmail.com
License: UNKNOWN
Platform: UNKNOWN
Classifier: Programming Language :: Python :: 3
Classifier: License :: OSI Approved :: GNU General Public License v3 (GPLv3)
Classifier: Operating System :: OS Independent
Requires-Python: >=3.6
